chemopy/__init__.py
chemopy/asa.py
chemopy/atom_property.py
chemopy/atom_types.py
chemopy/basak.py
chemopy/bcut.py
chemopy/charge.py
chemopy/chemopy.py
chemopy/connectivity.py
chemopy/constitution.py
chemopy/cpsa.py
chemopy/descs.json
chemopy/estate.py
chemopy/fingerprint.py
chemopy/fingerprint3d.py
chemopy/geary.py
chemopy/geo_opt.py
chemopy/geometric.py
chemopy/getmol.py
chemopy/kappa.py
chemopy/moe.py
chemopy/molproperty.py
chemopy/moran.py
chemopy/moreaubroto.py
chemopy/morse.py
chemopy/quanchem.py
chemopy/radius.py
chemopy/rdf.py
chemopy/topology.py
chemopy/utils.py
chemopy/vector3d.py
chemopy/whim.py
chemopy2-1.0.11.dist-info/licenses/LICENSE
chemopy2-1.0.11.dist-info/METADATA
chemopy2-1.0.11.dist-info/WHEEL
chemopy2-1.0.11.dist-info/top_level.txt
chemopy2-1.0.11.dist-info/RECORD
